dingtalk2/__init__.py
dingtalk2/constants.py
dingtalk2/dingtalk.py
dingtalk2/exceptions.py
dingtalk2/items.py
dingtalk2/logger.py
dingtalk2/request.py
dingtalk2/utils.py
dingtalk2-0.1.2.dist-info/WHEEL
dingtalk2-0.1.2.dist-info/METADATA
dingtalk2-0.1.2.dist-info/LICENSE
dingtalk2-0.1.2.dist-info/RECORD
