Metadata-Version: 2.1
Name: dingtalk2
Version: 0.1.2
Summary: 
Author: bopo
Author-email: ibopo@126.com
Requires-Python: >=3.8,<4.0
Classifier: Programming Language :: Python :: 3
Classifier: Programming Language :: Python :: 3.8
Classifier: Programming Language :: Python :: 3.9
Classifier: Programming Language :: Python :: 3.10
Classifier: Programming Language :: Python :: 3.11
Requires-Dist: asyncio (>=3.4.3,<4.0.0)
Requires-Dist: httpx (>=0.24.0,<0.25.0)
Requires-Dist: loguru (>=0.7.0,<0.8.0)
